arrendatools/__init__.py
arrendatools/actualiza_renta/__init__.py
arrendatools/actualiza_renta/actualizacion_renta.py
arrendatools/actualiza_renta/factory.py
arrendatools/actualiza_renta/ine.py
arrendatools/actualiza_renta/utils.py
arrendatools/actualiza_renta/tipos/__init__.py
arrendatools/actualiza_renta/tipos/cantidad_fija.py
arrendatools/actualiza_renta/tipos/ipc.py
arrendatools/actualiza_renta/tipos/irav.py
arrendatools/actualiza_renta/tipos/minimo_ipc_porcentaje.py
arrendatools/actualiza_renta/tipos/porcentaje.py
arrendatools_actualiza_renta-1.1.1.dist-info/licenses/LICENSE
arrendatools_actualiza_renta-1.1.1.dist-info/METADATA
arrendatools_actualiza_renta-1.1.1.dist-info/WHEEL
arrendatools_actualiza_renta-1.1.1.dist-info/top_level.txt
arrendatools_actualiza_renta-1.1.1.dist-info/RECORD
