Metadata-Version: 2.4
Name: arrendatools.actualiza_renta
Version: 1.1.1
Summary: Módulo de Python que realiza la actualización de rentas de alquiler por anualidades completas con el IPC (LAU) descrita en la web del INE de España.
Author-email: Jordi Morell <hokus@hotmail.com>
License: MIT
Classifier: Development Status :: 4 - Beta
Classifier: Intended Audience :: Developers
Classifier: License :: OSI Approved :: MIT License
Classifier: Programming Language :: Python :: 3.8
Classifier: Programming Language :: Python :: 3.9
Classifier: Programming Language :: Python :: 3.10
Classifier: Programming Language :: Python :: 3.11
Requires-Python: >=3.8
License-File: LICENSE
Requires-Dist: requests==2.32.5
Dynamic: license-file
